asposeslides/__init__.py
asposeslides/api.py
asposeslides/lib/aspose-slides-24.6.0-python.jar
aspose_slides_java-24.6.0.dist-info/METADATA
aspose_slides_java-24.6.0.dist-info/WHEEL
aspose_slides_java-24.6.0.dist-info/top_level.txt
aspose_slides_java-24.6.0.dist-info/RECORD
