Metadata-Version: 2.1
Name: aspose-slides-java
Version: 24.6.0
Summary: A powerful library for manipulating and converting PowerPoint (PPT, PPTX, ODT, OTP, POT, POTX, PPS, PPSX) files.
Home-page: https://products.aspose.com/slides/python-java/
Author: Aspose
License: https://company.aspose.com/legal/eula
Project-URL: Homepage, https://products.aspose.com/slides/python-java/
Project-URL: API Reference, https://reference.aspose.com/slides/python-java/
Project-URL: Blog, https://blog.aspose.com/category/slides/
Project-URL: Docs, https://docs.aspose.com/slides/python-java/
Project-URL: Free Support, https://forum.aspose.com/c/slides
Project-URL: Release Notes, https://releases.aspose.com/slides/python-java/release-notes/2024/aspose-slides-for-python-via-java-24-6-release-notes/
Project-URL: Search, https://search.aspose.com/
Project-URL: Temporary License, https://purchase.aspose.com/temporary-license
Keywords: ppt,pptx,potx,pot,pps,ppsx,odt,otp,import,export,convert,edit,pdf,xps,swf,svg,html,html5,powerpoint,presentation
Platform: Operating System :: Microsoft :: Windows
Platform: Operating System :: POSIX
Platform: Operating System :: Unix
Platform: Operating System :: MacOS
Classifier: License :: Other/Proprietary License
Classifier: License :: Free To Use But Restricted
Classifier: Intended Audience :: Education
Classifier: Intended Audience :: Developers
Classifier: Operating System :: MacOS
Classifier: Operating System :: Microsoft :: Windows
Classifier: Operating System :: POSIX
Classifier: Operating System :: Unix
Classifier: Programming Language :: Python :: 3.7
Classifier: Programming Language :: Python :: 3.8
Classifier: Programming Language :: Python :: 3.9
Classifier: Programming Language :: Python :: 3.10
Classifier: Programming Language :: Python :: 3.11
Classifier: Programming Language :: Python :: 3.12
Classifier: Topic :: Multimedia :: Graphics :: Presentation
Classifier: Topic :: Office/Business
Classifier: Topic :: Office/Business :: Office Suites
Classifier: Topic :: Software Development
Classifier: Topic :: Software Development :: Libraries
Requires-Python: >=3.7,<=3.12
Requires-Dist: JPype1 >=1.5.0
